
{
    "clients": {
        "Gsoil": {
            "version": "1.6.6",
            "platforms": {
                "linux": {
                    "x64": {
                        "download": {
                            "url": "https://github.com/Soilcoin/go-soil/releases/download/v1.6.6/gsoil-linux-amd64-1.6.6.tar.gz",
                            "type": "tar",
                            "md5": "fcd27c21a04f5b3280920b0e27aa533c",
                            "bin": "gsoil-linux-amd64-1.6.6/gsoil"
                        },
                        "bin": "gsoil",
                        "commands": {
                            "sanity": {
                                "args": ["version"],
                                "output": [ "Gsoil", "1.6.6" ]
                            }
                        }
                    },
                    "ia32": {
                        "download": {
                            "url": "https://github.com/Soilcoin/go-soil/releases/download/v1.6.6/gsoil-linux-386-1.6.6.tar.gz",
                            "type": "tar",
                            "md5": "ac03289e6292dde6d1d50e7c05558a3d",
                            "bin": "gsoil-linux-386-1.6.6/gsoil"
                        },
                        "bin": "gsoil",
                        "commands": {
                            "sanity": {
                                "args": ["version"],
                                "output": [ "Gsoil", "1.6.6" ]
                            }
                        }
                    }
                },
                "mac": {
                    "x64": {
                        "download": {
                            "url": "https://github.com/Soilcoin/go-soil/releases/download/v1.6.5/gsoil-darwin-amd64-1.6.6.tar.gz",
                            "type": "tar",
                            "md5": "3b22c273a5264234b0142c62c31656f0",
                            "bin": "gsoil-darwin-amd64-1.6.6/gsoil"
                        },
                        "bin": "gsoil",
                        "commands": {
                            "sanity": {
                                "args": ["version"],
                                "output": [ "Gsoil", "1.6.6" ]
                            }
                        }
                    }
                },
                "win": {
                    "x64": {
                        "download": {
                            "url": "https://github.com/Soilcoin/go-soil/releases/download/v1.6.5/gsoil-windows-amd64-1.6.6.zip",
                            "type": "zip",
                            "md5": "20b1a1af6e6fdeeedd7a2b77f6ff7277",
                            "bin": "gsoil-windows-amd64-1.6.6\\gsoil.exe"
                        },
                        "bin": "gsoil.exe",
                        "commands": {
                            "sanity": {
                                "args": ["version"],
                                "output": [ "Gsoil", "1.6.6" ]
                            }
                        }
                    },
                    "ia32": {
                        "download": {
                            "url": "https://github.com/Soilcoin/go-soil/releases/download/v1.6.6/gsoil-windows-386-1.6.6.zip",
                            "type": "zip",
                            "md5": "ff8a4ef2cb6f179b9a45012598629e99",
                            "bin": "gsoil-windows-386-1.6.6\\gsoil.exe"
                        },
                        "bin": "gsoil.exe",
                        "commands": {
                            "sanity": {
                                "args": ["version"],
                                "output": [ "Gsoil", "1.6.6" ]
                            }
                        }
                    }
                }
            }
        }
    }
}
